groqcli/__init__.py
groqcli/__main__.py
groqcli/cli.py
groqcli/config.py
groqcli/module_each.py
groq_tool-0.1.3.dist-info/METADATA
groq_tool-0.1.3.dist-info/WHEEL
groq_tool-0.1.3.dist-info/entry_points.txt
groq_tool-0.1.3.dist-info/top_level.txt
groq_tool-0.1.3.dist-info/RECORD
