Metadata-Version: 2.4
Name: groq-tool
Version: 0.1.3
Summary: A Modern Command-Line Tool for Interacting with Grog LLMs
Author: daisseur
Project-URL: Source, https://github.com/daisseur/groqcli
Classifier: Programming Language :: Python :: 3
Classifier: License :: OSI Approved :: MIT License
Classifier: Operating System :: OS Independent
Requires-Python: >=3.9
Requires-Dist: rich
Requires-Dist: requests
Requires-Dist: groq
Requires-Dist: dotenv
Requires-Dist: click
Dynamic: author
Dynamic: classifier
Dynamic: description
Dynamic: description-content-type
Dynamic: project-url
Dynamic: requires-dist
Dynamic: requires-python
Dynamic: summary
